{
  "id": "bowel-obstruction-deep-dive",
  "title": "Small Bowel Obstruction",
  "version": "1.0",
  "totalQuestions": 22,
  "estimatedTime": "35 minutes",
  "difficulty": "Intermediate",
  "targetAudience": "Medical Students, Residents",
  "category": "Surgery/GI",
  "icon": "\ud83e\ude7b",
  "objectives": [
    "Distinguish mechanical obstruction from ileus",
    "Recognize clinical and radiographic features of SBO",
    "Identify indications for surgical intervention",
    "Understand pathophysiology of strangulation",
    "Apply evidence-based management guidelines"
  ],
  "guidelineReferences": [
    {
      "name": "WSES Guidelines on SBO",
      "citation": "Ten Broek RP, et al. World J Emerg Surg. 2017;12:29",
      "url": "https://wjes.biomedcentral.com/articles/10.1186/s13017-017-0141-0"
    },
    {
      "name": "EAST Guidelines on SBO",
      "citation": "Maung AA, et al. J Trauma Acute Care Surg. 2012;73(5 Suppl 4):S362-9",
      "url": "https://www.east.org/education-resources/practice-management-guidelines/details/smallbowel-obstruction-evaluation-and-management-of"
    }
  ],
  "vignette": {
    "text": "A 62-year-old woman with history of hysterectomy and appendectomy presents with 2 days of crampy abdominal pain, nausea, vomiting, and inability to pass gas or stool. She has had 5-6 episodes of bilious vomiting. The pain comes in waves and is periumbilical.",
    "vitals": {
      "BP": "108/68 mmHg",
      "HR": "102 bpm",
      "RR": "18/min",
      "Temp": "99.8\u00b0F (37.7\u00b0C)",
      "SpO2": "98% on room air"
    },
    "physicalExam": {
      "general": "Appears uncomfortable, lying still between waves of pain",
      "abdomen": "Distended, tympanitic to percussion, high-pitched bowel sounds, diffuse tenderness without peritoneal signs, well-healed surgical scars",
      "hernia": "No inguinal or ventral hernias palpable"
    },
    "labs": {
      "BMP": "Na 132, K 3.2, Cl 92, CO2 30, BUN 28, Cr 1.3",
      "CBC": "WBC 12.4, Hgb 14.1",
      "lactate": "1.8 mmol/L"
    },
    "imaging": {
      "XR": "Multiple dilated loops of small bowel (>3 cm) with air-fluid levels, minimal colonic gas",
      "CT": "Transition point in mid-ileum with proximal small bowel dilation and decompressed distal bowel, small amount of free fluid, no pneumatosis or portal venous gas, likely adhesive band"
    }
  },
  "layers": [
    {
      "id": "recognition",
      "title": "Recognition & Diagnosis",
      "icon": "\ud83e\ude7b",
      "questions": [
        {
          "id": "dx-1",
          "stem": "The patient presents with crampy pain, vomiting, distension, and obstipation.",
          "question": "The classic tetrad of small bowel obstruction is:",
          "options": [
            "A. Continuous pain, fever, peritonitis, and shock",
            "B. Colicky pain, vomiting, distension, and obstipation",
            "C. Nausea, diarrhea, weight loss, and anemia",
            "D. Fever, pain, jaundice, and mass"
          ],
          "correctIndex": 1,
          "explanation": "The classic SBO tetrad: (1) Colicky/crampy abdominal pain (intermittent as bowel contracts against obstruction), (2) Vomiting (earlier and more profuse with proximal obstruction), (3) Abdominal distension, (4) Obstipation (no flatus or stool). This patient has all four.",
          "whyChain": [
            {
              "why": "Why is the pain colicky?",
              "answer": "The bowel proximal to obstruction undergoes vigorous contractions trying to push contents past the blockage. This creates waves of pain followed by relief. Continuous severe pain suggests strangulation.",
              "source": "StatPearls: Surgical Principles (NCBI Bookshelf)",
              "sourceUrl": "https://www.ncbi.nlm.nih.gov/books/NBK560551/"
            },
            {
              "why": "Why earlier vomiting with proximal obstruction?",
              "answer": "Less bowel to distend before vomiting reflex triggered. Proximal (jejunal) obstruction causes early, profuse, bilious vomiting. Distal obstruction causes later, more feculent vomiting.",
              "source": "WSES Guidelines",
              "sourceUrl": null
            }
          ],
          "sources": [
            {
              "text": "StatPearls: Small Bowel Obstruction. NCBI Bookshelf. Accessed January 14, 2026.",
              "url": "https://www.ncbi.nlm.nih.gov/books/NBK448095/"
            }
          ]
        },
        {
          "id": "dx-2",
          "stem": "CT shows a transition point with dilated proximal and decompressed distal bowel.",
          "question": "The 'transition point' on CT indicates:",
          "options": [
            "A. The point where enteral feeding should begin",
            "B. An area of bowel necrosis",
            "C. The junction between jejunum and ileum",
            "D. The site where caliber change indicates the location of obstruction"
          ],
          "correctIndex": 3,
          "explanation": "The transition point is where dilated proximal bowel (>3 cm for small bowel) meets decompressed distal bowel. This pinpoints the obstruction location and helps identify the cause (adhesion, hernia, mass, stricture). It's the most important CT finding for surgical planning.",
          "whyChain": [
            {
              "why": "Why does proximal bowel dilate?",
              "answer": "Accumulated swallowed air and intestinal secretions (8-10 L/day produced proximal to obstruction). The bowel can't absorb or pass this, so it dilates. Normal SB is \u22643 cm diameter.",
              "source": "Radiology Review",
              "sourceUrl": null
            },
            {
              "why": "What if no transition point is seen?",
              "answer": "Consider partial obstruction, intermittent obstruction, or ileus rather than mechanical SBO. May need repeat imaging if high clinical suspicion.",
              "source": "AJR Imaging Guidelines",
              "sourceUrl": null
            }
          ],
          "sources": [
            {
              "text": "StatPearls: Small Bowel Obstruction. NCBI Bookshelf. Accessed January 14, 2026.",
              "url": "https://www.ncbi.nlm.nih.gov/books/NBK448095/"
            }
          ]
        },
        {
          "id": "dx-3",
          "stem": "The patient has history of previous abdominal surgeries.",
          "question": "The most common cause of small bowel obstruction in developed countries is:",
          "options": [
            "A. Adhesions from previous surgery",
            "B. Crohn's disease stricture",
            "C. Malignancy",
            "D. Incarcerated hernia"
          ],
          "correctIndex": 0,
          "explanation": "Adhesions cause 65-75% of SBO in developed countries. Previous surgery is the major risk factor - more extensive surgery = more adhesions. Hernias are second (10-15%), then malignancy (10%). In countries with less surgical access, hernias are more common.",
          "whyChain": [
            {
              "why": "How do adhesions cause obstruction?",
              "answer": "Fibrous bands form between bowel loops and abdominal wall after surgery. Bowel can become kinked, compressed, or twisted by these bands, causing mechanical obstruction.",
              "source": "WSES Guidelines",
              "sourceUrl": null
            },
            {
              "why": "Which surgeries cause most adhesions?",
              "answer": "Colorectal, gynecologic, and appendectomy are highest risk. Open surgery causes more than laparoscopic. Lower abdominal surgery causes more than upper.",
              "source": "Lancet Adhesions Review",
              "sourceUrl": null
            }
          ],
          "sources": [
            {
              "text": "StatPearls: Small Bowel Obstruction. NCBI Bookshelf. Accessed January 14, 2026.",
              "url": "https://www.ncbi.nlm.nih.gov/books/NBK448095/"
            }
          ]
        }
      ]
    },
    {
      "id": "pathophysiology",
      "title": "Pathophysiology",
      "icon": "\ud83d\udd2c",
      "questions": [
        {
          "id": "path-1",
          "stem": "The labs show Na 132, K 3.2, hypovolemia (BUN/Cr ratio elevated).",
          "question": "The electrolyte abnormalities in SBO result from:",
          "options": [
            "A. Loss of gastric contents (vomiting) and third-spacing into bowel lumen",
            "B. Inadequate dietary intake alone",
            "C. Increased renal excretion",
            "D. SIADH from pain and stress"
          ],
          "correctIndex": 0,
          "explanation": "SBO causes massive fluid/electrolyte losses: (1) Vomiting loses gastric fluid (HCl, K+, H2O); (2) Sequestration into dilated bowel lumen (third-spacing); (3) Decreased absorption. Hypokalemic, hypochloremic metabolic alkalosis is classic. Dehydration is often severe.",
          "whyChain": [
            {
              "why": "How much fluid is lost?",
              "answer": "The GI tract normally secretes 8-10 L/day that is reabsorbed. In SBO, this is trapped proximally. Patients can sequester several liters into bowel lumen before presentation.",
              "source": "StatPearls: Surgical Principles (NCBI Bookshelf)",
              "sourceUrl": "https://www.ncbi.nlm.nih.gov/books/NBK560551/"
            },
            {
              "why": "Why metabolic alkalosis?",
              "answer": "Vomiting loses gastric acid (HCl). Loss of H+ causes alkalosis. Kidney compensates by excreting HCO3- but conserves Na+ (retains HCO3- instead). Volume depletion perpetuates alkalosis.",
              "source": "StatPearls: Metabolic Alkalosis",
              "sourceUrl": "https://www.ncbi.nlm.nih.gov/books/NBK560551/"
            }
          ],
          "sources": [
            {
              "text": "StatPearls: Surgical Principles (NCBI Bookshelf)",
              "url": "https://www.ncbi.nlm.nih.gov/books/NBK560551/"
            },
            {
              "text": "StatPearls: Metabolic Alkalosis",
              "url": "https://www.ncbi.nlm.nih.gov/books/NBK560551/"
            }
          ]
        },
        {
          "id": "path-2",
          "stem": "You are concerned about bowel viability.",
          "question": "Strangulation (compromised bowel blood supply) is suggested by all EXCEPT:",
          "options": [
            "A. Peritoneal signs on exam",
            "B. Normal lactate level",
            "C. Fever and tachycardia",
            "D. Continuous (non-colicky) severe pain"
          ],
          "correctIndex": 1,
          "explanation": "EXCEPT normal lactate - all others suggest strangulation. Strangulation signs: continuous severe pain (ischemia), fever, peritoneal signs, tachycardia, shock, elevated lactate, elevated WBC. However, strangulation can exist without elevated lactate - lactate is late and not sensitive.",
          "whyChain": [
            {
              "why": "Why does pain pattern change with strangulation?",
              "answer": "Colicky pain becomes continuous because ischemic bowel causes constant peritoneal irritation. 'Cramps turning to constant pain' is a red flag.",
              "source": "WSES Guidelines",
              "sourceUrl": null
            },
            {
              "why": "Why is lactate unreliable?",
              "answer": "Lactate rises late in ischemia (after cell death begins). By the time lactate elevates, necrosis may have occurred. Normal lactate doesn't rule out strangulation.",
              "source": "J Trauma Review",
              "sourceUrl": null
            },
            {
              "why": "What CT findings suggest strangulation?",
              "answer": "Decreased bowel wall enhancement, mesenteric haziness/fluid, closed-loop obstruction, bowel wall thickening, pneumatosis intestinalis (late), portal venous gas (late).",
              "source": "Radiology Findings",
              "sourceUrl": null
            }
          ],
          "sources": [
            {
              "text": "StatPearls: Small Bowel Obstruction. NCBI Bookshelf. Accessed January 14, 2026.",
              "url": "https://www.ncbi.nlm.nih.gov/books/NBK448095/"
            }
          ]
        }
      ]
    },
    {
      "id": "management",
      "title": "Management",
      "icon": "\ud83d\udc8a",
      "questions": [
        {
          "id": "mgmt-1",
          "stem": "This patient has adhesive SBO without signs of strangulation.",
          "question": "Initial management should include:",
          "options": [
            "A. NPO, nasogastric tube, IV fluid resuscitation, serial exams",
            "B. Colonoscopy to decompress",
            "C. Clear liquid diet and observation",
            "D. Immediate surgery"
          ],
          "correctIndex": 0,
          "explanation": "Uncomplicated adhesive SBO can often be managed non-operatively: NPO, NG decompression, aggressive IV fluids, electrolyte correction, and serial abdominal exams. 65-80% of adhesive SBO resolves without surgery. Key: frequent reassessment for strangulation signs.",
          "whyChain": [
            {
              "why": "Why NG tube?",
              "answer": "Decompresses the dilated proximal bowel, reduces vomiting/aspiration risk, may reduce bowel distension enough for obstruction to resolve, and allows monitoring of output.",
              "source": "WSES Guidelines",
              "sourceUrl": null
            },
            {
              "why": "How long to trial non-operative management?",
              "answer": "Generally 24-72 hours if patient stable and improving. If no resolution by 72 hours, surgery likely needed. Gastrografin can be diagnostic and therapeutic.",
              "source": "WSES Guidelines",
              "sourceUrl": null
            }
          ],
          "sources": [
            {
              "text": "StatPearls: Small Bowel Obstruction. NCBI Bookshelf. Accessed January 14, 2026.",
              "url": "https://www.ncbi.nlm.nih.gov/books/NBK448095/"
            }
          ]
        },
        {
          "id": "mgmt-2",
          "stem": "You are considering water-soluble contrast (Gastrografin) challenge.",
          "question": "Gastrografin in adhesive SBO:",
          "options": [
            "A. Replaces need for CT imaging",
            "B. Can predict need for surgery (contrast in colon by 24h = resolution) and may be therapeutic",
            "C. Is contraindicated due to aspiration risk",
            "D. Should only be given after 5 days of non-operative management"
          ],
          "correctIndex": 1,
          "explanation": "Gastrografin has dual benefit: (1) Diagnostic - contrast in colon by 4-24 hours predicts resolution without surgery (97% PPV); (2) Therapeutic - hyperosmolar contrast draws fluid into lumen, may reduce edema and help adhesion-related obstruction resolve. Meta-analyses support its use.",
          "whyChain": [
            {
              "why": "When should Gastrografin be given?",
              "answer": "After initial resuscitation and NG decompression, typically at 24-48 hours if not improving. Follow with X-ray at 4-24 hours. Contrast in colon = will resolve; no contrast = likely needs surgery.",
              "source": "Cochrane Review",
              "sourceUrl": null
            },
            {
              "why": "Any contraindications?",
              "answer": "Avoid if complete obstruction with suspected strangulation (needs surgery, not contrast). Avoid aspiration - ensure adequate NG decompression. Use with caution if perforation suspected (water-soluble is safer than barium).",
              "source": "WSES Guidelines",
              "sourceUrl": null
            }
          ],
          "sources": [
            {
              "text": "StatPearls: Small Bowel Obstruction. NCBI Bookshelf. Accessed January 14, 2026.",
              "url": "https://www.ncbi.nlm.nih.gov/books/NBK448095/"
            }
          ]
        },
        {
          "id": "mgmt-3",
          "stem": "On day 2, the patient develops worsening pain that is now constant, fever 101.5\u00b0F, and periumbilical tenderness with guarding.",
          "question": "The most appropriate next step is:",
          "options": [
            "A. Repeat CT scan",
            "B. Start TPN for nutritional support",
            "C. Continue observation for another 24 hours",
            "D. Urgent surgical exploration"
          ],
          "correctIndex": 3,
          "explanation": "The development of peritoneal signs (guarding, rebound), continuous pain (replacing colicky pain), and fever suggests strangulation/ischemia. This is a surgical emergency - do not delay for more imaging. Time is bowel - dead bowel means resection, complications, potential death.",
          "whyChain": [
            {
              "why": "What are absolute indications for surgery?",
              "answer": "Peritonitis, strangulation signs (fever, continuous pain, tachycardia), complete obstruction not resolving, closed-loop obstruction on CT, or clinical deterioration. Don't wait for lactate to rise.",
              "source": "WSES Guidelines",
              "sourceUrl": null
            },
            {
              "why": "What surgery is performed?",
              "answer": "Exploratory laparotomy (or laparoscopy in selected cases), lysis of adhesions, assessment of bowel viability. Necrotic bowel is resected. Primary anastomosis if viable; may need stoma if contamination/instability.",
              "source": "StatPearls: Surgical Principles (NCBI Bookshelf)",
              "sourceUrl": "https://www.ncbi.nlm.nih.gov/books/NBK560551/"
            }
          ],
          "sources": [
            {
              "text": "StatPearls: Small Bowel Obstruction. NCBI Bookshelf. Accessed January 14, 2026.",
              "url": "https://www.ncbi.nlm.nih.gov/books/NBK448095/"
            }
          ]
        },
        {
          "id": "mgmt-4",
          "stem": "The patient underwent successful adhesiolysis and recovered well.",
          "question": "To reduce future adhesion formation and SBO recurrence, which intervention has the most evidence?",
          "options": [
            "A. Adhesion barrier placement during surgery",
            "B. Nasogastric tube for 5 days postop",
            "C. Early postoperative ambulation",
            "D. Prophylactic antibiotics for 2 weeks"
          ],
          "correctIndex": 0,
          "explanation": "Adhesion barriers (hyaluronic acid-carboxymethylcellulose membrane) reduce adhesion formation and decrease risk of reoperation for SBO. Meta-analyses support their use in high-risk surgeries. Other strategies (minimally invasive surgery, meticulous technique) also help but have less robust evidence.",
          "whyChain": [
            {
              "why": "How do adhesion barriers work?",
              "answer": "They create a physical separation between bowel and peritoneum during healing when adhesions form (first 7 days). The barrier is absorbed after this critical period.",
              "source": "Cochrane Review Adhesion Prevention",
              "sourceUrl": null
            },
            {
              "why": "What about laparoscopic surgery?",
              "answer": "Laparoscopic surgery causes fewer adhesions than open surgery due to less tissue trauma, less peritoneal drying, and less foreign body reaction. Preferred when feasible.",
              "source": "WSES Guidelines",
              "sourceUrl": null
            }
          ],
          "sources": [
            {
              "text": "StatPearls: Small Bowel Obstruction. NCBI Bookshelf. Accessed January 14, 2026.",
              "url": "https://www.ncbi.nlm.nih.gov/books/NBK448095/"
            }
          ]
        }
      ]
    },
    {
      "id": "differentiation",
      "title": "Differential Diagnosis",
      "icon": "\ud83d\udd0d",
      "questions": [
        {
          "id": "diff-1",
          "stem": "You are distinguishing mechanical SBO from paralytic ileus.",
          "question": "Which finding favors mechanical SBO over ileus?",
          "options": [
            "A. Transition point on CT with distal decompression",
            "B. Diffuse abdominal distension without tenderness",
            "C. Absent bowel sounds",
            "D. Dilated small and large bowel on imaging"
          ],
          "correctIndex": 0,
          "explanation": "A discrete transition point with proximal dilation and distal decompression = mechanical obstruction. Ileus shows diffuse dilation of small AND large bowel without transition point. Bowel sounds are often hyperactive (high-pitched, tinkling) in early SBO but absent in ileus.",
          "whyChain": [
            {
              "why": "What causes ileus?",
              "answer": "Post-operative (most common), electrolyte disturbances (hypokalemia), medications (opioids), peritonitis, retroperitoneal processes, systemic illness. The bowel stops peristalsis but isn't mechanically blocked.",
              "source": "StatPearls: Ileus (NCBI Bookshelf)",
              "sourceUrl": "https://www.ncbi.nlm.nih.gov/books/NBK560551/"
            },
            {
              "why": "Why does differentiation matter?",
              "answer": "Ileus is managed by treating underlying cause - no surgery needed. Mechanical SBO may need surgery. Wrong diagnosis leads to wrong treatment.",
              "source": "StatPearls: Surgical Principles (NCBI Bookshelf)",
              "sourceUrl": "https://www.ncbi.nlm.nih.gov/books/NBK560551/"
            }
          ],
          "sources": [
            {
              "text": "StatPearls: Ileus (NCBI Bookshelf)",
              "url": "https://www.ncbi.nlm.nih.gov/books/NBK560551/"
            },
            {
              "text": "StatPearls: Surgical Principles (NCBI Bookshelf)",
              "url": "https://www.ncbi.nlm.nih.gov/books/NBK560551/"
            }
          ]
        }
      ]
    },
    {
      "id": "synthesis",
      "title": "Synthesis",
      "icon": "\ud83e\udde9",
      "questions": [
        {
          "id": "synth-1",
          "stem": "Integrating the approach to this patient...",
          "question": "The key decision in SBO management is distinguishing:",
          "options": [
            "A. Proximal vs distal obstruction",
            "B. Simple (non-strangulated) vs complicated (strangulated) SBO",
            "C. First episode vs recurrent SBO",
            "D. Complete vs incomplete obstruction"
          ],
          "correctIndex": 1,
          "explanation": "The critical distinction is simple (uncomplicated) vs strangulated (complicated) SBO. Simple SBO can be managed non-operatively with high success rates. Strangulated SBO requires URGENT surgery to prevent bowel necrosis and death. Every clinical decision aims to identify or exclude strangulation.",
          "whyChain": [
            {
              "why": "What drives the urgency of this distinction?",
              "answer": "Strangulated bowel = ischemia = necrosis within hours. Necrotic bowel leads to perforation, peritonitis, sepsis, and death. Time from strangulation onset to surgery determines outcome.",
              "source": "WSES Guidelines",
              "sourceUrl": null
            },
            {
              "why": "How does this guide serial exams?",
              "answer": "Non-operative patients need frequent reassessment (q4-6h) for conversion to strangulation. Any worsening = surgical consultation. The goal is early detection before necrosis occurs.",
              "source": "EAST Guidelines",
              "sourceUrl": null
            }
          ],
          "sources": [
            {
              "text": "StatPearls: Small Bowel Obstruction. NCBI Bookshelf. Accessed January 14, 2026.",
              "url": "https://www.ncbi.nlm.nih.gov/books/NBK448095/"
            }
          ]
        }
      ]
    }
  ],
  "references": [
    {
      "title": "ATLS Guidelines - Trauma Management",
      "url": "https://www.ncbi.nlm.nih.gov/books/NBK430685/",
      "source": "StatPearls"
    },
    {
      "title": "ACS Wound Healing Guidelines",
      "url": "https://www.ncbi.nlm.nih.gov/books/NBK470443/",
      "source": "StatPearls"
    },
    {
      "title": "Appendicitis Diagnosis - NCBI",
      "url": "https://www.ncbi.nlm.nih.gov/books/NBK493193/",
      "source": "StatPearls"
    }
  ],
  "platformLinks": [
    {
      "type": "adventure",
      "text": "\ud83d\uddfa\ufe0f Bowel Obstruction Adventure",
      "url": "adventure-cases/upj-obstruction-crt.html"
    },
    {
      "type": "deepDive",
      "text": "\ud83d\udcda Bowel Obstruction Deep Dive",
      "url": "bowel-obstruction-deep-dive.json"
    }
  ],
  "mcqs": [
    {
      "stem": "Which of the following is the MOST important initial step in evaluating a patient with suspected bowel obstruction?",
      "options": [
        {
          "text": "Obtain a thorough history and physical examination",
          "correct": true,
          "explanation": "A comprehensive history and physical examination is the foundation of clinical reasoning in bowel obstruction. It guides all subsequent diagnostic and management decisions."
        },
        {
          "text": "Order advanced imaging immediately",
          "correct": false,
          "explanation": "Advanced imaging may be indicated but should be guided by clinical findings, not ordered reflexively."
        },
        {
          "text": "Start empiric treatment before evaluation",
          "correct": false,
          "explanation": "Treatment should generally follow an appropriate diagnostic evaluation unless the patient is critically unstable."
        },
        {
          "text": "Consult a specialist before any workup",
          "correct": false,
          "explanation": "Initial evaluation should be performed by the treating physician; specialist consultation follows based on findings."
        }
      ]
    },
    {
      "stem": "A patient presents with classic features of bowel obstruction. Which clinical reasoning principle is MOST important in avoiding diagnostic error?",
      "options": [
        {
          "text": "Search satisficing - stop looking after the first diagnosis",
          "correct": false,
          "explanation": "Premature closure (stopping the diagnostic process too early) is a common cognitive error that leads to missed diagnoses."
        },
        {
          "text": "Consider the differential diagnosis systematically",
          "correct": true,
          "explanation": "Systematic consideration of differential diagnoses, including must-not-miss conditions, is essential for avoiding premature closure and anchoring bias."
        },
        {
          "text": "Rely primarily on pattern recognition",
          "correct": false,
          "explanation": "While pattern recognition (System 1 thinking) is useful, it should be balanced with analytical reasoning (System 2) to avoid cognitive biases."
        },
        {
          "text": "Order every available test to rule out all possibilities",
          "correct": false,
          "explanation": "Indiscriminate testing leads to false positives, unnecessary procedures, and increased cost without improving diagnostic accuracy."
        }
      ]
    },
    {
      "stem": "When managing bowel obstruction, which approach best supports evidence-based practice?",
      "options": [
        {
          "text": "Follow institutional protocols regardless of patient factors",
          "correct": false,
          "explanation": "Evidence-based practice integrates best evidence with clinical expertise AND patient values/circumstances."
        },
        {
          "text": "Base decisions solely on clinical experience",
          "correct": false,
          "explanation": "Clinical experience is valuable but can introduce bias; it should be combined with current evidence."
        },
        {
          "text": "Integrate current best evidence with clinical expertise and patient values",
          "correct": true,
          "explanation": "Evidence-based medicine is the conscientious integration of best research evidence, clinical expertise, and patient values in making clinical decisions."
        },
        {
          "text": "Always defer to the most recent published study",
          "correct": false,
          "explanation": "Individual studies should be appraised for quality and relevance; systematic reviews and guidelines generally provide stronger evidence."
        }
      ]
    },
    {
      "stem": "A 25-year-old male arrives after a motorcycle accident with distended neck veins, hypotension, and absent breath sounds on the left. What is the most appropriate immediate intervention?",
      "options": [
        {
          "text": "Needle decompression at the 2nd intercostal space, midclavicular line, left side",
          "correct": true,
          "explanation": "This classic triad (JVD, hypotension, absent breath sounds) is tension pneumothorax \u2014 a clinical diagnosis requiring IMMEDIATE needle decompression before imaging. Per ATLS, insert a 14-gauge needle at the 2nd ICS midclavicular line (or 5th ICS anterior axillary line) followed by tube thoracostomy."
        },
        {
          "text": "Obtain a portable chest X-ray to confirm the diagnosis",
          "correct": false,
          "explanation": "Tension pneumothorax is a CLINICAL diagnosis. Waiting for imaging delays life-saving treatment and can result in cardiovascular collapse and death. Treat first, image after."
        },
        {
          "text": "Perform emergent pericardiocentesis",
          "correct": false,
          "explanation": "While Beck's triad (JVD, hypotension, muffled heart sounds) suggests cardiac tamponade, the ABSENT BREATH SOUNDS distinguish tension pneumothorax. Tamponade does not cause absent breath sounds."
        },
        {
          "text": "Intubate and start positive pressure ventilation",
          "correct": false,
          "explanation": "Positive pressure ventilation in an undecompressed tension pneumothorax will worsen the condition by forcing more air into the pleural space, accelerating cardiovascular collapse."
        }
      ]
    }
  ],
  "sections": [
    {
      "title": "Overview",
      "content": "Comprehensive review of Bowel Obstruction."
    },
    {
      "title": "Clinical Approach",
      "content": "Systematic approach to Bowel Obstruction including recognition, diagnosis, and management."
    },
    {
      "title": "Key Points",
      "content": "Evidence-based clinical pearls for Bowel Obstruction."
    }
  ]
}