{
  "id": "acute-pancreatitis",
  "presentation": "Acute Pancreatitis",
  "category": "gastrointestinal",
  "difficulty": 3,
  "rotations": ["medicine", "surgery"],
  "board": "admitting",
  "edHandoff": {
    "summary": "42-year-old male presenting with severe epigastric pain radiating to back after heavy alcohol use over the weekend. Lipase 1,840. CT shows peripancreatic inflammation, no necrosis. 2L NS given, morphine 4mg x2. Pain improved to 6/10. Vitals improved but still tachycardic at 98.",
    "disposition": "Admit to medicine for IV fluids, pain management, and monitoring"
  },
  "demographics": {
    "ageRange": [35, 55],
    "genderDistribution": { "male": 0.65, "female": 0.35 },
    "nameOptions": {
      "male": ["Mark Sullivan", "Anthony Russo", "Derek Jameson", "Howard Lam", "Craig Thornton"],
      "female": ["Brenda McCarthy", "Carolyn Fisher", "Debra Huang", "Evelyn Price", "Francesca Romano"]
    }
  },
  "sources": [
    {
      "name": "Acute Pancreatitis - StatPearls",
      "type": "statpearls",
      "url": "https://www.ncbi.nlm.nih.gov/books/NBK482468/",
      "accessDate": "2026-02",
      "citedFor": ["diagnosis", "severity scoring", "management"]
    },
    {
      "name": "AGA Guidelines on Initial Management of Acute Pancreatitis",
      "type": "guideline",
      "url": "https://www.gastrojournal.org/article/S0016-5085(18)30076-3/fulltext",
      "accessDate": "2026-02",
      "citedFor": ["fluid resuscitation", "nutrition", "severity assessment"]
    }
  ],
  "variant": {
    "id": "alcohol-pancreatitis-v1",
    "diagnosis": "Acute Alcohol-Induced Pancreatitis (Moderately Severe)",
    "acuity": 3,
    "patient": {
      "personalityTraits": ["minimizes alcohol use", "uncomfortable discussing drinking", "wants quick fix"],
      "communicationStyle": "Initially vague about alcohol consumption. Becomes more open if asked non-judgmentally. Frustrated about dietary restrictions.",
      "emotionalState": "In pain, slightly defensive about alcohol history",
      "medicalLiteracy": "low"
    },
    "clinicalFacts": {
      "chiefComplaint": {
        "patientPhrasing": ["feels like someone stabbed me in the stomach", "pain goes straight through to my back", "can't eat anything"],
        "location": "Epigastric, boring through to mid-back",
        "radiation": ["mid-back", "bilateral flanks"],
        "onset": "Started 12 hours ago after a weekend of heavy drinking (bachelor party)",
        "severity": "9/10 at worst, now 6/10 with IV meds",
        "aggravating": ["eating", "lying flat", "deep breathing"],
        "relieving": ["leaning forward", "IV pain medications", "NPO"]
      },
      "associatedSymptoms": {
        "present": [
          "nausea and vomiting (bilious, non-bloody, 4-5 episodes)",
          "anorexia (can't tolerate anything by mouth)",
          "fever (low-grade, 100.6°F)"
        ],
        "absent": ["hematemesis", "melena", "jaundice", "diarrhea", "chest pain"]
      },
      "pmh": [
        "One prior episode of pancreatitis (2 years ago, also alcohol-related, managed conservatively)",
        "GERD",
        "Hypertension"
      ],
      "medications": [
        { "name": "Omeprazole", "dose": "20mg daily" },
        { "name": "Amlodipine", "dose": "5mg daily" }
      ],
      "allergies": [],
      "socialHistory": {
        "smoking": "Half pack per day for 15 years",
        "alcohol": "Reports '4-5 drinks on weekends' — but weekend binge was 15+ drinks over 2 days at bachelor party. Likely underreporting baseline use.",
        "drugs": "Marijuana occasionally",
        "occupation": "Sales representative"
      },
      "familyHistory": ["Father: alcoholism", "No pancreatic cancer"],
      "riskFactors": {
        "present": ["alcohol use (most common cause)", "prior pancreatitis episode", "smoking"],
        "absent": ["gallstones (RUQ US normal)", "hypertriglyceridemia (TG 180)", "ERCP", "medications", "trauma"]
      }
    },
    "physicalExam": {
      "vitalSigns": { "BP": "132/82", "HR": "98", "RR": "18", "Temp": "100.6°F", "SpO2": "97% on RA" },
      "general": "Middle-aged male, appears uncomfortable, lying in fetal position, prefers leaning forward",
      "cardiovascular": "Mild tachycardia, regular, no murmurs",
      "pulmonary": "Clear bilaterally. Decreased breath sounds at left base (small reactive pleural effusion possible).",
      "abdominal": "Epigastric tenderness with guarding. No rebound. Decreased bowel sounds. No palpable mass. No Grey Turner or Cullen signs.",
      "extremities": "No edema"
    },
    "diagnostics": {
      "labs": [
        { "test": "Lipase", "value": "1,840", "unit": "U/L", "ref": "10-140", "status": "critical", "note": ">3x ULN — meets diagnostic criteria for acute pancreatitis" },
        { "test": "Amylase", "value": "620", "unit": "U/L", "ref": "25-125", "status": "abnormal", "note": "Elevated but less specific than lipase" },
        { "test": "WBC", "value": "14.8", "unit": "K/uL", "ref": "4.5-11.0", "status": "abnormal", "note": "Inflammatory response" },
        { "test": "BUN", "value": "28", "unit": "mg/dL", "ref": "7-20", "status": "abnormal", "note": "Elevated — dehydration. BUN >20 is part of BISAP score." },
        { "test": "Creatinine", "value": "1.3", "unit": "mg/dL", "ref": "0.7-1.3", "status": "normal", "note": "High-normal, monitor with aggressive hydration" },
        { "test": "Glucose", "value": "162", "unit": "mg/dL", "ref": "70-100", "status": "abnormal", "note": "Stress response vs pancreatic endocrine dysfunction" },
        { "test": "Calcium", "value": "8.2", "unit": "mg/dL", "ref": "8.5-10.5", "status": "abnormal", "note": "Mildly low — saponification, monitor closely (Ranson's criterion)" },
        { "test": "ALT", "value": "45", "unit": "U/L", "ref": "7-56", "status": "normal", "note": "Normal — argues against gallstone etiology" },
        { "test": "AST", "value": "52", "unit": "U/L", "ref": "10-40", "status": "abnormal", "note": "Mildly elevated — possible alcohol effect" },
        { "test": "Triglycerides", "value": "180", "unit": "mg/dL", "ref": "<150", "status": "abnormal", "note": "Mildly elevated but <1,000 — not the cause" },
        { "test": "Lactate", "value": "1.8", "unit": "mmol/L", "ref": "<2.0", "status": "normal", "note": "Normal — no perfusion deficit currently" }
      ],
      "imaging": [
        { "study": "RUQ Ultrasound", "findings": "No gallstones. No biliary dilation. Common bile duct 4mm. Gallbladder wall normal.", "impression": "No cholelithiasis. Gallstone pancreatitis unlikely." },
        { "study": "CT Abdomen/Pelvis with IV contrast", "findings": "Diffuse pancreatic enlargement with peripancreatic fat stranding and small amount of peripancreatic fluid. No pancreatic necrosis (uniform enhancement). Small left pleural effusion. No pseudocyst or abscess.", "impression": "Acute interstitial pancreatitis without necrosis. Peripancreatic inflammatory changes." }
      ]
    },
    "admittingOrders": {
      "diet": "NPO initially. Advance to low-fat solid diet when pain improving (within 24 hours if tolerated — early feeding is preferred over prolonged NPO).",
      "ivFluids": "Lactated Ringer's at 200-250mL/hr for initial 12-24 hours (goal-directed — target urine output >0.5mL/kg/hr, BUN trending down, HR normalizing)",
      "painManagement": "Hydromorphone 0.5-1mg IV q3h PRN (avoid meperidine — no evidence it's superior; acetaminophen 1g IV/PO q6h scheduled as adjunct)",
      "monitoring": "Vitals q4h. Strict I&O. Foley only if unable to void. Trend lipase (does NOT need to normalize before advancing diet). BMP q12h x 48 hours. CBC daily.",
      "antiemetics": "Ondansetron 4mg IV q6h PRN",
      "dvtProphylaxis": "Enoxaparin 40mg SQ daily or SCDs if contraindicated",
      "consultations": "GI consult if clinical worsening, suspected necrosis, or need for ERCP. Social work/addiction counseling for alcohol use."
    },
    "teaching": {
      "correctDiagnosis": "Acute Alcohol-Induced Pancreatitis",
      "keyLearningPoints": [
        "Diagnosis requires 2 of 3: characteristic abdominal pain, lipase >3x ULN, imaging findings",
        "Severity scoring: BISAP (BUN>25, impaired mental status, SIRS, age>60, pleural effusion) — this patient scores 2 (BUN, pleural effusion)",
        "LR is preferred over NS for fluid resuscitation (less hyperchloremic acidosis, may reduce SIRS)",
        "Early feeding (within 24 hours) is superior to prolonged NPO — advances recovery",
        "Gallstone pancreatitis is excluded by normal RUQ US and normal ALT — alcohol is the cause",
        "Second episode of alcohol-induced pancreatitis = strong indication for alcohol cessation counseling"
      ],
      "mustNotMiss": [
        "Necrotizing pancreatitis (worsening despite treatment — repeat CT at 72 hours if not improving)",
        "Organ failure (monitor for ARDS, AKI, cardiovascular failure — Revised Atlanta criteria)",
        "Infected necrosis (fever + worsening after initial improvement at day 7-10)"
      ],
      "commonPitfalls": [
        "Keeping patient NPO for days — early enteral nutrition improves outcomes",
        "Over-ordering lipase — don't trend it to determine when to feed (use clinical improvement instead)",
        "Under-resuscitating — these patients lose massive third-space fluid",
        "Over-resuscitating — can worsen edema and respiratory status. Use goal-directed targets.",
        "Not addressing alcohol use — two episodes = chronic pancreatitis risk without intervention"
      ],
      "attendingQuestions": "The ED is giving you a clear diagnosis here. Your job is to assess severity, plan resuscitation, and anticipate complications. What scoring system helps you predict severity? What's your fluid strategy, and how will you know it's working?"
    }
  }
}
